hyperon_das/__init__.py
hyperon_das/api.py
hyperon_das/exceptions.py
hyperon_das/factory.py
hyperon_das/logger.py
hyperon_das/pattern_matcher/__init__.py
hyperon_das/pattern_matcher/constants.py
hyperon_das/pattern_matcher/pattern_matcher.py
hyperon_das/utils.py
capozzoli_testando_hyperon_das-0.1.0.dist-info/METADATA
capozzoli_testando_hyperon_das-0.1.0.dist-info/WHEEL
capozzoli_testando_hyperon_das-0.1.0.dist-info/RECORD
