Metadata-Version: 2.1
Name: capozzoli-testando-hyperon-das
Version: 0.1.0
Summary: Query Engine API for Distributed AtomSpace
Author: marcocapozzoli
Author-email: marcocapozzoli90@gmail.com
Requires-Python: >=3.8.5,<4.0.0
Classifier: Programming Language :: Python :: 3
Classifier: Programming Language :: Python :: 3.9
Classifier: Programming Language :: Python :: 3.10
Classifier: Programming Language :: Python :: 3.11
Requires-Dist: capozzoli-testando-hyperon-das-atomdb (>=0.1.0,<0.2.0)
Requires-Dist: python-dotenv (>=1.0.0,<2.0.0)
